synthetix/__init__.py
synthetix/constants.py
synthetix/synthetix.py
synthetix/contracts/__init__.py
synthetix/contracts/contracts.py
synthetix/contracts/deployments/__init__.py
synthetix/contracts/deployments/10/PerpsV2Market.json
synthetix/contracts/deployments/10/PerpsV2MarketData.json
synthetix/contracts/deployments/10/USDProxy.json
synthetix/contracts/deployments/10/WETH.json
synthetix/contracts/deployments/10/sUSD.json
synthetix/contracts/deployments/420/AccountProxy.json
synthetix/contracts/deployments/420/CoreProxy.json
synthetix/contracts/deployments/420/PerpsAccountProxy.json
synthetix/contracts/deployments/420/PerpsMarketProxy.json
synthetix/contracts/deployments/420/PerpsV2Market.json
synthetix/contracts/deployments/420/PerpsV2MarketData.json
synthetix/contracts/deployments/420/SpotMarketProxy.json
synthetix/contracts/deployments/420/TrustedMulticallForwarder.json
synthetix/contracts/deployments/420/USDProxy.json
synthetix/contracts/deployments/420/WETH.json
synthetix/contracts/deployments/420/sUSD.json
synthetix/contracts/deployments/84531/AccountProxy.json
synthetix/contracts/deployments/84531/CoreProxy.json
synthetix/contracts/deployments/84531/ERC7412.json
synthetix/contracts/deployments/84531/PerpsAccountProxy.json
synthetix/contracts/deployments/84531/PerpsMarketProxy.json
synthetix/contracts/deployments/84531/SpotMarketProxy.json
synthetix/contracts/deployments/84531/TrustedMulticallForwarder.json
synthetix/contracts/deployments/84531/USDProxy.json
synthetix/contracts/deployments/84531/WETH.json
synthetix/core/__init__.py
synthetix/core/constants.py
synthetix/core/core.py
synthetix/perps/__init__.py
synthetix/perps/constants.py
synthetix/perps/perps.py
synthetix/pyth/__init__.py
synthetix/pyth/constants.py
synthetix/pyth/pyth.py
synthetix/queries/__init__.py
synthetix/queries/config.py
synthetix/queries/gql.py
synthetix/queries/queries.py
synthetix/spot/__init__.py
synthetix/spot/constants.py
synthetix/spot/spot.py
synthetix/utils/__init__.py
synthetix-1.0.3.dist-info/METADATA
synthetix-1.0.3.dist-info/WHEEL
synthetix-1.0.3.dist-info/top_level.txt
synthetix-1.0.3.dist-info/RECORD
